drf_sso/__init__.py
drf_sso/apps.py
drf_sso/exception.py
drf_sso/settings.py
drf_sso/urls.py
drf_sso/views.py
drf_sso/handover/__init__.py
drf_sso/handover/handover.py
drf_sso/management/__init__.py
drf_sso/management/commands/__init__.py
drf_sso/management/commands/sp_meta.py
drf_sso/providers/__init__.py
drf_sso/providers/auth_provider.py
drf_sso/providers/cas_provider.py
drf_sso/providers/oauth_provider.py
drf_sso/providers/oidc_provider.py
drf_sso/providers/registry.py
drf_sso/providers/saml_provider.py
drf_sso/providers/user_population.py
drf_sso/providers/cas/__init__.py
drf_sso/providers/cas/cas.py
drf_sso/providers/oauth/__init__.py
drf_sso/providers/oauth/oauth.py
drf_sso/providers/oidc/__init__.py
drf_sso/providers/oidc/oidc.py
drf_sso/providers/samlsp/__init__.py
drf_sso/providers/samlsp/config.py
drf_sso/providers/samlsp/metadata.py
drf_sso/providers/samlsp/request.py
drf_sso/providers/samlsp/response.py
drf_sso/providers/samlsp/saml.py
drf_sso/providers/samlsp/xmlsign_utils.py
drf_sso-0.0.2b3.dist-info/METADATA
drf_sso-0.0.2b3.dist-info/WHEEL
drf_sso-0.0.2b3.dist-info/top_level.txt
drf_sso-0.0.2b3.dist-info/RECORD
